alan_ta/__init__.py
alan_ta/alan_ta.py
AlanTA-0.101.15.dist-info/METADATA
AlanTA-0.101.15.dist-info/WHEEL
AlanTA-0.101.15.dist-info/top_level.txt
AlanTA-0.101.15.dist-info/RECORD
